verilog/DelayModelling/MixDelay/model_tb.v
module xor1(out, a, b, c);
output reg out;
input a, b, c;

always @(a, b, c)
    #10 out = #6 (a^b^c);
endmodule

module xortb;
reg a, b, c;
wire out;

xor1 x1(.out(out), .a(a), .b(b), .c(c));

initial begin
    #10 a = 1'b0; b = 1'b0; c = 1'b0;
    #22 a = 1'b1; b = 1'b0; c = 1'b0;
    #36 a = 1'b0; b = 1'b1; c = 1'b1;
    #25 a = 1'b1; b = 1'b1; c = 1'b1;
end

initial begin
    $monitor("Time: %t, A: %b, B: %b, C: %b, Output: %b", $time, a, b, c, out);
    
    $dumpfile("wv.vcd");
    $dumpvars(0, xortb);

    #200;
    $finish;
end
endmodule

verilog/DelayModelling/MixDelay/wv.vcd
$date
	Mon Sep 29 10:50:48 2025
$end
$version
	Icarus Verilog
$end
$timescale
	1s
$end
$scope module xortb $end
$var wire 1 ! out $end
$var reg 1 " a $end
$var reg 1 # b $end
$var reg 1 $ c $end
$scope module x1 $end
$var wire 1 " a $end
$var wire 1 # b $end
$var wire 1 $ c $end
$var reg 1 ! out $end
$upscope $end
$upscope $end
$enddefinitions $end
$comment Show the parameter values. $end
$dumpall
$end
#0
$dumpvars
x$
x#
x"
x!
$end
#10
0$
0#
0"
#26
0!
#32
1"
#48
1!
#68
1$
1#
0"
#84
0!
#93
1"
#109
1!
