verilog/DelayModelling/PinToPinDelay/model_tb.v
module delay22(q, a, b, c, d);
output q;
input a, b, c, d;
wire e, f;

specify
    (a=>q) = 10;
    (b=>q) = 12;
    (c=>q) = 18; 
    (d=>q) = 22;
endspecify

and a1(e, a, b);
and a2(f, c, d);
and a3(q, e, f);
endmodule

module tb;
reg a, b, c, d;
wire q;
delay22 d2(q, a, b, c, d);

initial begin
    {a, b, c, d} = 4'b1111;
    #25 {a, b, c, d} = 4'b1110;
    #25 {a, b, c, d} = 4'b1111;
    #25 {a, b, c, d} = 4'b1101;
    #25 {a, b, c, d} = 4'b1111;
    #25 {a, b, c, d} = 4'b1011;
    #25 {a, b, c, d} = 4'b1111;
    #25 {a, b, c, d} = 4'b0111;
    #25 {a, b, c, d} = 4'b1111;
end

initial begin
    $monitor("Time: %t, A: %b, B: %b, C: %b, D: %b, Output: %b", $time, a, b, c, d, q);

    $dumpfile("wv.vcd");
    $dumpvars(0, tb);

    #200;
    $finish;
end
endmodule

verilog/DelayModelling/PinToPinDelay/wv.vcd
$date
	Mon Sep 29 13:04:33 2025
$end
$version
	Icarus Verilog
$end
$timescale
	1s
$end
$scope module tb $end
$var wire 1 ! q $end
$var reg 1 " a $end
$var reg 1 # b $end
$var reg 1 $ c $end
$var reg 1 % d $end
$scope module d2 $end
$var wire 1 " a $end
$var wire 1 # b $end
$var wire 1 $ c $end
$var wire 1 % d $end
$var wire 1 & e $end
$var wire 1 ' f $end
$var wire 1 ! q $end
$upscope $end
$upscope $end
$enddefinitions $end
$comment Show the parameter values. $end
$dumpall
$end
#0
$dumpvars
1'
1&
1%
1$
1#
1"
1!
$end
#25
0!
0'
0%
#50
1!
1'
1%
#75
0!
0'
0$
#100
1!
1'
1$
#125
0!
0&
0#
#150
1!
1&
1#
#175
0!
0&
0"
#200
1!
1&
1"
