verilog/DelayModelling/GateDelay/model_tb.v
module delay1(out, a, b, c);

output out;
input a, b, c;
wire w1, w2, w3, w4;
wire enable = 1;

and #1 a1(w1, a, b);
or #3 o1(w2, w1, c);
not #5 n1(w3, w2);
xor #6 x1(w4, w3, w1);
bufif1 #2 b1(out, w4, enable);
endmodule

module xortb;

reg a, b, c;
wire out;
delay1 d1(.out(out), .a(a), .b(b), .c(c));

initial begin
    #10 a = 1'b0; b = 1'b0; c = 1'b0;
    #10 a = 1'b0; b = 1'b0; c = 1'b1;
    #36 a = 1'b0; b = 1'b1; c = 1'b1;
    #40 a = 1'b1; b = 1'b1; c = 1'b1;
    #30 a = 1'b1; b = 1'b1; c = 1'b0;
    #30 a = 1'b1; b = 1'b0; c = 1'b1;
end

initial begin 
    $monitor("Outputs, Time: %t, A: %b, B: %b, C: %b, Output: %b \n", $time, a, b, c, out);

    $dumpfile("wv.vcd");
    $dumpvars(0, xortb);

    #200;
    $finish;
end
endmodule

verilog/DelayModelling/GateDelay/wv.vcd
$date
	Mon Sep 29 12:04:53 2025
$end
$version
	Icarus Verilog
$end
$timescale
	1s
$end
$scope module xortb $end
$var wire 1 ! out $end
$var reg 1 " a $end
$var reg 1 # b $end
$var reg 1 $ c $end
$scope module d1 $end
$var wire 1 " a $end
$var wire 1 # b $end
$var wire 1 $ c $end
$var wire 1 % enable $end
$var wire 1 ! out $end
$var wire 1 & w1 $end
$var wire 1 ' w2 $end
$var wire 1 ( w3 $end
$var wire 1 ) w4 $end
$upscope $end
$upscope $end
$enddefinitions $end
$comment Show the parameter values. $end
$dumpall
$end
#0
$dumpvars
x)
x(
x'
x&
1%
x$
x#
x"
x!
$end
#10
0$
0#
0"
#11
0&
#14
0'
#19
1(
#20
1$
#23
1'
#25
1)
#27
1!
#28
0(
#34
0)
#36
0!
