verilog/MUX_8X1/mux_8x1.v
module mux_8x1(out, i0, i1, i2, i3, i4, i5, i6, i7, s0, s1, s2);
output out; 
input i0, i1, i2, i3, i4, i5, i6, i7, s0, s1, s2;

assign out = (s2 == 0) ? ((s1 == 0) ? ((s0 == 0) ? i0 : i1) : ((s0 == 0) ? i2 : i3)) : ((s1 == 0) ? ((s0 == 0) ? i4 : i5) : ((s0 == 0) ? i6 : i7)); 
endmodule

verilog/MUX_8X1/mux_8x1_tb.v
module tb;

reg i0, i1, i2, i3, i4, i5, i6, i7, s0, s1, s2;
wire out;
mux_8x1 m1(out, i0, i1, i2, i3, i4, i5, i6, i7, s0, s1, s2);

initial begin
i0 = 1; i1 = 0; i2 = 0; i3 = 0; i4 = 0; i5 = 0; i6 = 0; i7 = 0; s2 = 0; s1 = 0; s0 = 0;
#10;
i0 = 0; i1 = 1; i2 = 0; i3 = 0; i4 = 0; i5 = 0; i6 = 0; i7 = 0; s2 = 0; s1 = 0; s0 = 1;
#10;
i0 = 0; i1 = 0; i2 = 1; i3 = 0; i4 = 0; i5 = 0; i6 = 0; i7 = 0; s2 = 0; s1 = 1; s0 = 0;
#10
i0 = 0; i1 = 0; i2 = 0; i3 = 1; i4 = 0; i5 = 0; i6 = 0; i7 = 0; s2 = 0; s1 = 1; s0 = 1;
#10
i0 = 0; i1 = 0; i2 = 0; i3 = 0; i4 = 1; i5 = 0; i6 = 0; i7 = 0; s2 = 1; s1 = 0; s0 = 0;
#10;
i0 = 0; i1 = 0; i2 = 0; i3 = 0; i4 = 0; i5 = 1; i6 = 0; i7 = 0; s2 = 1; s1 = 0; s0 = 1;
#10;
i0 = 0; i1 = 0; i2 = 0; i3 = 0; i4 = 0; i5 = 0; i6 = 1; i7 = 0; s2 = 1; s1 = 1; s0 = 0;
#10;
i0 = 0; i1 = 0; i2 = 0; i3 = 0; i4 = 0; i5 = 0; i6 = 0; i7 = 1; s2 = 1; s1 = 1; s0 = 1; 

end

initial begin
$monitor("Time: %t, i0: %d, i1: %d, i2: %d, i3: %d, i4: %d, i5: %d, i6: %d, i7: %d, s0: %d, s1: %d, s0: %d, Output: %d", $time, i0, i1, i2, i3, i4, i5, i6, i7, s0, s1, s2, out);
end

initial begin
$dumpfile("mux.vcd");
$dumpvars(0, tb);
end

initial begin
#200;
$finish;
end

endmodule

verilog/MUX_8X1/mux.vcd
$date
	Wed Sep 24 13:02:25 2025
$end
$version
	Icarus Verilog
$end
$timescale
	1s
$end
$scope module tb $end
$var wire 1 ! out $end
$var reg 1 " i0 $end
$var reg 1 # i1 $end
$var reg 1 $ i2 $end
$var reg 1 % i3 $end
$var reg 1 & i4 $end
$var reg 1 ' i5 $end
$var reg 1 ( i6 $end
$var reg 1 ) i7 $end
$var reg 1 * s0 $end
$var reg 1 + s1 $end
$var reg 1 , s2 $end
$scope module m1 $end
$var wire 1 " i0 $end
$var wire 1 # i1 $end
$var wire 1 $ i2 $end
$var wire 1 % i3 $end
$var wire 1 & i4 $end
$var wire 1 ' i5 $end
$var wire 1 ( i6 $end
$var wire 1 ) i7 $end
$var wire 1 * s0 $end
$var wire 1 + s1 $end
$var wire 1 , s2 $end
$var wire 1 ! out $end
$upscope $end
$upscope $end
$enddefinitions $end
$comment Show the parameter values. $end
$dumpall
$end
#0
$dumpvars
0,
0+
0*
0)
0(
0'
0&
0%
0$
0#
1"
1!
$end
#10
1*
1#
0"
#20
1!
0*
1+
1$
0#
#30
1*
1%
0$
#40
1!
0*
0+
1,
1&
0%
#50
1*
1'
0&
#60
1!
0*
1+
1(
0'
#70
1*
1)
0(
