verilog/DelayModelling/EdgeSensitve/model_tb.v
module setup_hold12(q, d, clock);
    input d, clock;
    output reg q;

    specify 
        (posedge clock => (q+:d)) = (10,8);
    endspecify

    always @(posedge clock)
        q <= d;
endmodule

module setup_hold12_tb;
    reg d;
    reg clock = 0;
    wire q; 

    setup_hold12 sh1(.q(q), .d(d), .clock(clock));
    initial 
        forever #7 clock = ~clock;

    initial begin
        d = 1'b0;
        #15 d = 1'b1;
        #17 d = 1'b0;
        #19 d = 1'b1;
        #15 d = 1'b0;
        #14 d = 1'b1;
    end

    initial begin
        $monitor("Time: %t, D: %b, Q: %b", $time, d, q);
        
        $dumpfile("wv.vcd");
        $dumpvars(0, setup_hold12_tb);

        #200;
        $finish;
    end
endmodule

verilog/DelayModelling/EdgeSensitve/local/wv.vcd
$date
	Tue Sep 30 10:56:02 2025
$end
$version
	Icarus Verilog
$end
$timescale
	1s
$end
$scope module setup_hold12_tb $end
$var wire 1 ! q $end
$var reg 1 " clock $end
$var reg 1 # d $end
$scope module sh1 $end
$var wire 1 " clock $end
$var wire 1 # d $end
$var reg 1 ! q $end
$upscope $end
$upscope $end
$enddefinitions $end
$comment Show the parameter values. $end
$dumpall
$end
#0
$dumpvars
0#
0"
x!
$end
#7
0!
1"
#14
0"
#15
1#
#21
1!
1"
#28
0"
#32
0#
#35
0!
1"
#42
0"
#49
1"
#51
1#
#56
0"
#63
1!
1"
#66
0#
#70
0"
#77
0!
1"
#80
1#
#84
0"
#91
1!
1"
