verilog/DelayModelling/LumpedDelay/model_tb.v
module M(out, a, b, c, d);
output out;
input a, b, c, d;
wire e, f;

and a1(e, a, b);
and a2(f, c, d);
and #11 a3(out, e, f);
endmodule

module tb;

reg a, b, c, d;
wire out;
M m1(out, a, b, c, d);

initial begin
    {a,b,c,d} = 4'b1111;
    #10 {a,b,c,d} = 4'b1110;
    #10 {a,b,c,d} = 4'b1111;
    #10 {a,b,c,d} = 4'b1101;
    #10 {a,b,c,d} = 4'b1111;
    #10 {a,b,c,d} = 4'b1011;
    #10 {a,b,c,d} = 4'b1111;
    #10 {a,b,c,d} = 4'b0111;
    #10 {a,b,c,d} = 4'b1111;
end
initial begin
    $monitor("Time: %t, A: %b, B: %b, C: %b, D:%b, Output: %b", $time, a, b, c, d, out);

    $dumpfile("wv.vcd");
    $dumpvars(0, tb);

    #200;
    $finish;
end
endmodule

verilog/DelayModelling/LumpedDelay/wv.vcd
$date
	Mon Sep 29 12:34:03 2025
$end
$version
	Icarus Verilog
$end
$timescale
	1s
$end
$scope module tb $end
$var wire 1 ! out $end
$var reg 1 " a $end
$var reg 1 # b $end
$var reg 1 $ c $end
$var reg 1 % d $end
$scope module m1 $end
$var wire 1 " a $end
$var wire 1 # b $end
$var wire 1 $ c $end
$var wire 1 % d $end
$var wire 1 & e $end
$var wire 1 ' f $end
$var wire 1 ! out $end
$upscope $end
$upscope $end
$enddefinitions $end
$comment Show the parameter values. $end
$dumpall
$end
#0
$dumpvars
1'
1&
1%
1$
1#
1"
x!
$end
#10
0'
0%
#20
1'
1%
#30
0'
0$
#40
1'
1$
#50
0&
0#
#60
1&
1#
#70
0&
0"
#80
1&
1"
#91
1!
