verilog/DelayModelling/DFF/model_tb.v
module dff(q, d, clk);

input d, clk;
output reg q;

specify
    specparam tRise_clk_q = 150;
    specparam tFall_clk_q = 200;
    specparam tSetup = 70;
    (clk => q) = (tRise_clk_q, tFall_clk_q);
endspecify

always @(posedge clk)
    q<=d;
endmodule

module tb;

reg d;
reg clk = 0;
wire q;

dff dut(q, d, clk);
always #15 clk =~ clk;
initial begin
    #5 d = 0;
    #30 d = 1;
    #30 d = 0;
    #30 d = 1;
end

initial begin
    $monitor("Time: %t, D: %b, Q: %b", $time, d, q);

    $dumpfile("wv.vcd");
    $dumpvars(0, tb);

    #200;
    $finish;
end
endmodule

verilog/DelayModelling/DFF/wv.vcd
$date
	Mon Sep 29 13:12:20 2025
$end
$version
	Icarus Verilog
$end
$timescale
	1s
$end
$scope module tb $end
$var wire 1 ! q $end
$var reg 1 " clk $end
$var reg 1 # d $end
$scope module dut $end
$var wire 1 " clk $end
$var wire 1 # d $end
$var parameter 32 $ tFall_clk_q $end
$var parameter 32 % tRise_clk_q $end
$var parameter 32 & tSetup $end
$var reg 1 ! q $end
$upscope $end
$upscope $end
$enddefinitions $end
$comment Show the parameter values. $end
$dumpall
b1000110 &
b10010110 %
b11001000 $
$end
#0
$dumpvars
x#
0"
x!
$end
#5
0#
#15
0!
1"
#30
0"
#35
1#
#45
1!
1"
#60
0"
#65
0#
#75
0!
1"
#90
0"
#95
1#
#105
1!
1"
