verilog/Behavioral/test.v
module tb;
reg [15:0] data = 16'b 1111_1111_0000_0000;

reg clk = 0;
initial 
    forever #10 clk = ~clk;

always @(negedge clk)
begin
    data[15:8] <= data[7:0];
    data[7:0]  <= data[15:8];
end

initial begin
    $monitor("Time: %t, Data: %b", $time, data);

    $dumpfile("wv.vcd");
    $dumpvars(0, tb);

    #300;
    $finish;
end
endmodule

verilog/Behavioral/wv.vcd
$date
	Tue Sep 30 13:11:37 2025
$end
$version
	Icarus Verilog
$end
$timescale
	1s
$end
$scope module tb $end
$var reg 1 ! clk $end
$var reg 16 " data [15:0] $end
$upscope $end
$enddefinitions $end
$comment Show the parameter values. $end
$dumpall
$end
#0
$dumpvars
b1111111100000000 "
0!
$end
#10
1!
#20
b11111111 "
0!
#30
1!
#40
b1111111100000000 "
0!
#50
1!
#60
b11111111 "
0!
#70
1!
#80
b1111111100000000 "
0!
#90
1!
#100
b11111111 "
0!
#110
1!
#120
b1111111100000000 "
0!
#130
1!
#140
b11111111 "
0!
#150
1!
#160
b1111111100000000 "
0!
#170
1!
#180
b11111111 "
0!
#190
1!
#200
b1111111100000000 "
0!
#210
1!
#220
b11111111 "
0!
#230
1!
#240
b1111111100000000 "
0!
#250
1!
#260
b11111111 "
0!
#270
1!
#280
b1111111100000000 "
0!
#290
1!
#300
b11111111 "
0!
