verilog/DelayModelling/MUXD/model_tb.v
module mux8(in1, in2, s, q);
output [3:0] q;
input [3:0] in1, in2;
input s;

specify
    (in1 => q) = (3, 4);
    (in2 => q) = (2, 3);
    (s *> q) = 1;
endspecify

assign q = s ? in2:in1;
endmodule

module tb;
reg [3:0] in1, in2;
reg s;
wire [3:0] out;

mux8 m1(in1, in2, s, out);

initial begin
    s = 0; 
    #20 s = 1;
    #20 s = 0; 
    #20 s = 1;
    #20 s = 0; 
    #20 s = 1; 
    #20 s = 0;
    #20 s = 1;
    #20 s = 0;
    #20 s = 1;
    #20 s = 0;
    #20 s = 1;
end

initial begin
    #4 in1 = 4'b0000;
    in2 = 4'b0000;
    #4 in1 = 4'b0001;
    in2 = 4'b0100;
    #4 in1 = 4'b0110;
    in2 = 4'b1010;
    #4 in1 = 4'b0111;
    in2 = 4'b1111;
end

initial begin
    $monitor("Time: %t, In1: %b, In2: %b, S: %b, Out: %b", $time, in1, in2, s, out);

    $dumpfile("wv.vcd");
    $dumpvars(0, tb);

    #500;
    $finish;
end
endmodule

verilog/DelayModelling/MUXD/wv.vcd
$date
	Mon Sep 29 13:26:22 2025
$end
$version
	Icarus Verilog
$end
$timescale
	1s
$end
$scope module tb $end
$var wire 4 ! out [3:0] $end
$var reg 4 " in1 [3:0] $end
$var reg 4 # in2 [3:0] $end
$var reg 1 $ s $end
$scope module m1 $end
$var wire 4 % in1 [3:0] $end
$var wire 4 & in2 [3:0] $end
$var wire 1 $ s $end
$var wire 4 ' q [3:0] $end
$upscope $end
$upscope $end
$enddefinitions $end
$comment Show the parameter values. $end
$dumpall
$end
#0
$dumpvars
bx '
bx &
bx %
0$
bx #
bx "
bx !
$end
#4
b0 !
b0 '
b0 #
b0 &
b0 "
b0 %
#8
b1 !
b1 '
b100 #
b100 &
b1 "
b1 %
#12
b110 !
b110 '
b1010 #
b1010 &
b110 "
b110 %
#16
b111 !
b111 '
b1111 #
b1111 &
b111 "
b111 %
#20
b1111 !
b1111 '
1$
#40
b111 !
b111 '
0$
#60
b1111 !
b1111 '
1$
#80
b111 !
b111 '
0$
#100
b1111 !
b1111 '
1$
#120
b111 !
b111 '
0$
#140
b1111 !
b1111 '
1$
#160
b111 !
b111 '
0$
#180
b1111 !
b1111 '
1$
#200
b111 !
b111 '
0$
#220
b1111 !
b1111 '
1$
